odoo8_addon_account_due_list_days_overdue-8.0.0.1.0-py2.7-nspkg.pth
odoo_addons/account_due_list_days_overdue/__openerp__.py
odoo_addons/account_due_list_days_overdue/__init__.py
odoo_addons/account_due_list_days_overdue/README.rst
odoo_addons/account_due_list_days_overdue/security/ir.model.access.csv
odoo_addons/account_due_list_days_overdue/models/account_move_line.py
odoo_addons/account_due_list_days_overdue/models/account_overdue_term.py
odoo_addons/account_due_list_days_overdue/models/__init__.py
odoo_addons/account_due_list_days_overdue/views/account_overdue_term_view.xml
odoo_addons/account_due_list_days_overdue/views/account_move_line_view.xml
odoo_addons/account_due_list_days_overdue/tests/__init__.py
odoo_addons/account_due_list_days_overdue/tests/test_account_due_list_days_overdue.py
odoo_addons/account_due_list_days_overdue/demo/account_overdue_term_demo.xml
odoo_addons/account_due_list_days_overdue/static/description/icon.png
odoo8_addon_account_due_list_days_overdue-8.0.0.1.0.dist-info/top_level.txt
odoo8_addon_account_due_list_days_overdue-8.0.0.1.0.dist-info/WHEEL
odoo8_addon_account_due_list_days_overdue-8.0.0.1.0.dist-info/RECORD
odoo8_addon_account_due_list_days_overdue-8.0.0.1.0.dist-info/metadata.json
odoo8_addon_account_due_list_days_overdue-8.0.0.1.0.dist-info/DESCRIPTION.rst
odoo8_addon_account_due_list_days_overdue-8.0.0.1.0.dist-info/METADATA
odoo8_addon_account_due_list_days_overdue-8.0.0.1.0.dist-info/namespace_packages.txt
